tessa/__init__.py
tessa/price/__init__.py
tessa/price/coingecko.py
tessa/price/price.py
tessa/price/types.py
tessa/price/yahoo.py
tessa/search/__init__.py
tessa/search/coingecko.py
tessa/search/search.py
tessa/search/search_result.py
tessa/search/yahoo.py
tessa/sources/__init__.py
tessa/sources/low_level_rate_limiter.py
tessa/sources/rate_limiter.py
tessa/sources/sources.py
tessa/sources/sources_directory.py
tessa/sources/sourcetype.py
tessa/symbol/__init__.py
tessa/symbol/extended_symbol.py
tessa/symbol/geo/__init__.py
tessa/symbol/geo/countrynames.py
tessa/symbol/geo/jurisdiction2region.py
tessa/symbol/symbol.py
tessa/symbol/symbolcollection.py
tessa-0.10.0.dist-info/LICENSE
tessa-0.10.0.dist-info/METADATA
tessa-0.10.0.dist-info/WHEEL
tessa-0.10.0.dist-info/RECORD
