Metadata-Version: 2.3
Name: tessa
Version: 0.10.0
Summary: Find financial assets and get their price history without worrying about different APIs or rate limiting.
License: MIT
Keywords: python,finance,investing,financial-analysis,investment-analysis,financial-data,coingecko,pycoingecko,yahoo,yahoo-finance,yfinance
Author: ymyke
Requires-Python: >=3.10,<4.0
Classifier: License :: OSI Approved :: MIT License
Classifier: Programming Language :: Python :: 3
Classifier: Programming Language :: Python :: 3.10
Classifier: Programming Language :: Python :: 3.11
Classifier: Programming Language :: Python :: 3.12
Classifier: Programming Language :: Python :: 3.13
Requires-Dist: PyYAML (>=6)
Requires-Dist: matplotlib (>=3.5)
Requires-Dist: pendulum (>=3.0)
Requires-Dist: pycoingecko (>=3.0)
Requires-Dist: seaborn (>=0.12)
Requires-Dist: yfinance (>=0.2.58)
Project-URL: Documentation, https://ymyke.github.io/tessa/tessa.html
Project-URL: Homepage, https://github.com/ymyke/tessa
Project-URL: Repository, https://github.com/ymyke/tessa
